secrets_loader/__init__.py
secrets_loader/secrets_loader.py
azkv_secrets_loader-0.0.5.dist-info/METADATA
azkv_secrets_loader-0.0.5.dist-info/WHEEL
azkv_secrets_loader-0.0.5.dist-info/top_level.txt
azkv_secrets_loader-0.0.5.dist-info/RECORD
